<list><item n="1">A-Gf_S1_28-001r.jpg</item><item n="2">A-Gf_S1_28-001v.jpg</item><item n="3">A-Gf_S1_28-002r.jpg</item><item n="4">A-Gf_S1_28-002v.jpg</item><item n="5">A-Gf_S1_28-003r.jpg</item><item n="6">A-Gf_S1_28-003v.jpg</item><item n="7">A-Gf_S1_28-004r.jpg</item><item n="8">A-Gf_S1_28-004v.jpg</item><item n="9">A-Gf_S1_28-005r.jpg</item><item n="10">A-Gf_S1_28-005v.jpg</item><item n="11">A-Gf_S1_28-006r.jpg</item><item n="12">A-Gf_S1_28-006v.jpg</item><item n="13">A-Gf_S1_28-007r.jpg</item><item n="14">A-Gf_S1_28-007v.jpg</item><item n="15">A-Gf_S1_28-008r.jpg</item><item n="16">A-Gf_S1_28-008v.jpg</item><item n="17">A-Gf_S1_28-009r.jpg</item><item n="18">A-Gf_S1_28-009v.jpg</item><item n="19">A-Gf_S1_28-010r.jpg</item><item n="20">A-Gf_S1_28-010v.jpg</item><item n="21">A-Gf_S1_28-011r.jpg</item><item n="22">A-Gf_S1_28-011v.jpg</item><item n="23">A-Gf_S1_28-012r.jpg</item><item n="24">A-Gf_S1_28-012v.jpg</item><item n="25">A-Gf_S1_28-013r.jpg</item><item n="26">A-Gf_S1_28-013v.jpg</item><item n="27">A-Gf_S1_28-014r.jpg</item><item n="28">A-Gf_S1_28-014v.jpg</item><item n="29">A-Gf_S1_28-a001r.jpg</item><item n="30">A-Gf_S1_28-a001v.jpg</item><item n="31">A-Gf_S1_28-a002r.jpg</item><item n="32">A-Gf_S1_28-a002v.jpg</item><item n="33">A-Gf_S1_28-BR.jpg</item><item n="34">A-Gf_S1_28-HD.jpg</item><item n="35">A-Gf_S1_28-HDS.jpg</item><item n="36">A-Gf_S1_28-VD.jpg</item><item n="37">A-Gf_S1_28-VDS.jpg</item></list>